<?xml version="1.0" standalone="yes"?>  <DATAPACKET Version="2.0"><METADATA><FIELDS><FIELD attrname="id" fieldtype="i4"/><FIELD attrname="Usuario" fieldtype="i4"/><FIELD attrname="Nome" fieldtype="string" WIDTH="20"/><FIELD attrname="sexo" fieldtype="i4"/><FIELD attrname="RG" fieldtype="string" WIDTH="20"/><FIELD attrname="CPF" fieldtype="string" WIDTH="20"/><FIELD attrname="Email" fieldtype="string" WIDTH="20"/><FIELD attrname="Nascimento" fieldtype="string" WIDTH="20"/><FIELD attrname="Cidade" fieldtype="string" WIDTH="20"/><FIELD attrname="Uf" fieldtype="string" WIDTH="20"/><FIELD attrname="Telefone" fieldtype="string" WIDTH="20"/><FIELD attrname="Rua" fieldtype="string" WIDTH="20"/><FIELD attrname="Numero" fieldtype="string" WIDTH="20"/><FIELD attrname="Complemento" fieldtype="string" WIDTH="20"/><FIELD attrname="Bairro" fieldtype="string" WIDTH="20"/></FIELDS><PARAMS CHANGE_LOG="1 0 4 2 0 4 3 1 8 4 2 8 5 0 4 6 0 4 7 0 4 8 0 4 9 0 4 10 5 8 11 4 8"/></METADATA><ROWDATA><ROW RowState="5" id="1" Usuario="1" Nome="atimilson fortes per" sexo="0" RG="2312313" CPF="555.555.555-55" Email="" Nascimento="22/22/2222" Cidade="313131" Uf="12" Telefone="(32)13123-3232" Rua="2313131313132" Numero="3233" Complemento="2323" Bairro="3232332"/><ROW RowState="5" id="2" Usuario="1" Nome="maria joaquina" sexo="0" RG="85585858" CPF="555.555.555-55" Email="maria123@gmail" Nascimento="21/21/2121" Cidade="vg" Uf="MT" Telefone="(23)43333-3333" Rua="av ddsdss" Numero="dadad" Complemento="daddddd" Bairro="bbbbbbbbb"/><ROW RowState="12" id="1" Usuario="1" Nome="atimilson fortes per" sexo="0" RG="2312313" CPF="555.555.555-55" Email="atimilson@" Nascimento="22/22/2222" Cidade="313131" Uf="12" Telefone="(32)13123-3232" Rua="2313131313132" Numero="3233" Complemento="2323" Bairro="3232332"/><ROW RowState="13" id="2" Usuario="1" Nome="maria joaquina" sexo="1" RG="85585858" CPF="555.555.555-55" Email="maria123@gmail" Nascimento="21/21/2121" Cidade="vg" Uf="MT" Telefone="(23)43333-3333" Rua="av ddsdss" Numero="dadad" Complemento="daddddd" Bairro="bbbbbbbbb"/><ROW RowState="5" id="1" Usuario="2" Nome="maria joaquina" sexo="0" RG="333333333" CPF="333.333.333-33" Email="3asdadadada" Nascimento="22/12/2222" Cidade="asdasd" Uf="FF" Telefone="(33)33333-3333" Rua="asdassada" Numero="dsada" Complemento="sdasdasdd" Bairro="fffffff"/><ROW RowState="4" id="3" Usuario="1" Nome="joaquim" sexo="0" RG="qwewe" CPF="231.233.333-33" Email="111111122" Nascimento="11/11/1111" Cidade="111111111111" Uf="11" Telefone="(11)1    -" Rua="11112" Numero="22222" Complemento="222222" Bairro="2222"/><ROW RowState="4" id="4" Usuario="2" Nome="pedro" sexo="0" RG="1233131" CPF="123.213.123-12" Email="1231313" Nascimento="23/12/3123" Cidade="1312312" Uf="12" Telefone="(12)1    -" Rua="121212212" Numero="131312" Complemento="123123" Bairro="3131312312"/><ROW RowState="4" id="5" Usuario="1" Nome="joao garcia" sexo="0" RG="131333333444" CPF="444.444.444-44" Email="44444444444" Nascimento="44/44/4444" Cidade="4444444444444" Uf="44" Telefone="(44)44444-4444" Rua="44444444444444444" Numero="444444" Complemento="4444444444" Bairro="444444444444"/><ROW RowState="4" id="6" Usuario="1" Nome="jhgjgjhgjhgjhghj" sexo="0" RG="jhghgj" CPF="666.666.666-66" Email="6666666666" Nascimento="22/22/2222" Cidade="666666" Uf="22" Telefone="(22)22222-22" Rua="2222222" Numero="2222" Complemento="2222222" Bairro="2222222222"/><ROW RowState="12" id="1" Usuario="2" Nome="jhgjgjhgjhgjhghj" sexo="0" RG="jhghgj" CPF="666.666.666-66" Email="6666666666" Nascimento="22/22/2222" Cidade="666666" Uf="22" Telefone="(22)22222-22" Rua="2222222" Numero="2222" Complemento="2222222" Bairro="2222222222"/><ROW RowState="12" id="2" Usuario="1" Nome="joao garcia" sexo="0" RG="131333333444" CPF="444.444.444-44" Email="44444444444" Nascimento="44/44/4444" Cidade="4444444444444" Uf="44" Telefone="(44)44444-4444" Rua="44444444444444444" Numero="444444" Complemento="4444444444" Bairro="444444444444"/></ROWDATA></DATAPACKET>